you_mp3/__init__.py
you_mp3/__main__.py
you_mp3/__utils.py
you_mp3/downloader.py
you_mp3/metadata.py
you_mp3-3.1.1.dist-info/LICENSE
you_mp3-3.1.1.dist-info/METADATA
you_mp3-3.1.1.dist-info/WHEEL
you_mp3-3.1.1.dist-info/entry_points.txt
you_mp3-3.1.1.dist-info/RECORD
