Metadata-Version: 2.1
Name: You-MP3
Version: 3.1.1
Summary: Tool for downloading music with added metadata
Home-page: https://pypi.org/project/You-MP3/
License: Unlicense
Keywords: conversion,download,metadata,music,youtube
Author: RuanMiguel-DRD
Author-email: ruanmigueldrd@outlook.com
Requires-Python: >=3.10,<4.0
Classifier: Development Status :: 5 - Production/Stable
Classifier: Environment :: Console
Classifier: Intended Audience :: End Users/Desktop
Classifier: License :: OSI Approved
Classifier: License :: OSI Approved :: The Unlicense (Unlicense)
Classifier: Natural Language :: English
Classifier: Operating System :: OS Independent
Classifier: Programming Language :: Python :: 3
Classifier: Programming Language :: Python :: 3.10
Classifier: Programming Language :: Python :: 3.11
Classifier: Programming Language :: Python :: 3.12
Classifier: Topic :: Multimedia :: Sound/Audio
Classifier: Topic :: Software Development :: Libraries :: Python Modules
Requires-Dist: mutagen (>=1.47.0,<2.0.0)
Requires-Dist: pillow (>=10.4.0,<11.0.0)
Requires-Dist: yt-dlp (>=2024.8.6,<2025.0.0)
Project-URL: Repository, https://github.com/RuanMiguel-DRD/You-MP3
